little_helpers/__init__.py
little_helpers/array_tools.py
little_helpers/geometry.py
little_helpers/hydrogel_conversions.py
little_helpers/math_functions.py
little_helpers/math_to_word.py
little_helpers/num_derive.py
little_helpers/statsmodel_wrapper.py
little_helpers-0.0.6.dist-info/LICENSE
little_helpers-0.0.6.dist-info/METADATA
little_helpers-0.0.6.dist-info/WHEEL
little_helpers-0.0.6.dist-info/top_level.txt
little_helpers-0.0.6.dist-info/RECORD
