Metadata-Version: 2.1
Name: little-helpers
Version: 0.0.6
Summary: little helper functions
Home-page: https://github.com/AlexanderSouthan/little_helpers
Author: Alexander Southan
Author-email: alexander.southan@web.de
Project-URL: Bug Tracker, https://github.com/AlexanderSouthan/little_helpers/issues
Classifier: Programming Language :: Python :: 3
Classifier: License :: OSI Approved :: MIT License
Classifier: Operating System :: OS Independent
Requires-Python: >=3.6
License-File: LICENSE
Requires-Dist: numpy
Requires-Dist: scikit-learn
Requires-Dist: scipy
Requires-Dist: statsmodels
Requires-Dist: matplotlib
Requires-Dist: sympy
Requires-Dist: python-docx
Requires-Dist: latex2mathml
Requires-Dist: lxml
